[{"username": "ayush005", "name": "Ayush Sinha", "email": "b22153@students.iitmandi.ac.in", "password": "$argon2id$v=19$m=65536,t=3,p=4$AS9MvRx3bUmULn57FEUPyw$yG8YPXEHiekSTmkYFX28Ru9HF/CDAHHe+iq7po6dVBE"}, {"username": "saatvikmangal", "name": "Saatvik Mangal", "email": "mangalsaatvik@gmail.com", "password": "$argon2id$v=19$m=65536,t=3,p=4$ioeJahX3yUt9pq+SxXxjbg$JIIxIzllffqkAZUEjYXdyc/RyCi/C57F4AtY/F0dwvE"}, {"username": "APL07", "name": "APL", "email": "testit12973@gmail.com", "password": "$argon2id$v=19$m=65536,t=3,p=4$ijVOlBLcj6x1O1CcC75chw$goDtwZQ0pzBZsDbGnsHtsUc3eM3zWaHEsOCJjaxsMOo"}]